drvd_bench/__init__.py
drvd_bench/choice_metric.py
drvd_bench/data_loader.py
drvd_bench/mapper.py
drvd_bench/qwen2.5vl_7b_demo.ipynb
drvd_bench/report_metric.py
drvd_bench-0.2.2.dist-info/LICENSE
drvd_bench-0.2.2.dist-info/METADATA
drvd_bench-0.2.2.dist-info/WHEEL
drvd_bench-0.2.2.dist-info/top_level.txt
drvd_bench-0.2.2.dist-info/RECORD
