Metadata-Version: 2.1
Name: drvd-bench
Version: 0.2.2
Summary: Benchmark toolkit for DrVD
Author-email: Yin Xu <xuyin23@mails.tsinghua.edu.cn>
License: MIT License
Project-URL: Homepage, https://github.com/Jerry-Boss/DrVD-Bench
Project-URL: Issues, https://github.com/Jerry-Boss/DrVD-Bench/issues
Requires-Python: >=3.9
License-File: LICENSE
Requires-Dist: bert-score
Requires-Dist: tqdm
Requires-Dist: nltk
Requires-Dist: openai
Requires-Dist: Pillow
Requires-Dist: torch
Requires-Dist: transformers
